MANIFEST.in
README.txt
setup.py
docs/HISTORY.txt
src/infrae/__init__.py
src/infrae.wsgi.egg-info/PKG-INFO
src/infrae.wsgi.egg-info/SOURCES.txt
src/infrae.wsgi.egg-info/dependency_links.txt
src/infrae.wsgi.egg-info/entry_points.txt
src/infrae.wsgi.egg-info/namespace_packages.txt
src/infrae.wsgi.egg-info/not-zip-safe
src/infrae.wsgi.egg-info/requires.txt
src/infrae.wsgi.egg-info/top_level.txt
src/infrae/wsgi/__init__.py
src/infrae/wsgi/authenticator.py
src/infrae/wsgi/configure.zcml
src/infrae/wsgi/debugging.py
src/infrae/wsgi/errors.py
src/infrae/wsgi/ftesting.zcml
src/infrae/wsgi/headers.py
src/infrae/wsgi/interfaces.py
src/infrae/wsgi/log.py
src/infrae/wsgi/paster.py
src/infrae/wsgi/publisher.py
src/infrae/wsgi/ravenplugin.py
src/infrae/wsgi/response.py
src/infrae/wsgi/traverser.py
src/infrae/wsgi/utils.py
src/infrae/wsgi/virtualhosting.py
src/infrae/wsgi/log_templates/errorlogview.pt
src/infrae/wsgi/testing/__init__.py
src/infrae/wsgi/testing/intercept.py
src/infrae/wsgi/testing/layer.py
src/infrae/wsgi/testing/request.py
src/infrae/wsgi/tests/__init__.py
src/infrae/wsgi/tests/fixtures.py
src/infrae/wsgi/tests/mockers.py
src/infrae/wsgi/tests/test_functional.py
src/infrae/wsgi/tests/test_headers.py
src/infrae/wsgi/tests/test_publisher.py
src/infrae/wsgi/tests/test_request.py
src/infrae/wsgi/tests/test_response.py
src/infrae/wsgi/tests/test_testlayer.py