Metadata-Version: 1.0
Name: infrae.wsgi
Version: 2.2.1
Summary: WSGI support for Zope 2
Home-page: http://svn.infrae.com/infrae.wsgi/trunk
Author: Sylvain Viollon
Author-email: info@infrae.com
License: ZPL
Keywords: zope2 wsgi silva infrae
Platform: UNKNOWN
Classifier: Environment :: Web Environment
Classifier: Intended Audience :: Developers
Classifier: License :: OSI Approved :: Zope Public License
Classifier: Programming Language :: Python
Classifier: Topic :: Software Development :: Libraries :: Python Modules
Classifier: Framework :: Zope2
